django_surveyplus-1.0.2.dist-info/licenses/LICENSE
survey/__init__.py
survey/admin.py
survey/apps.py
survey/forms.py
survey/models.py
survey/signals.py
survey/tests.py
survey/urls.py
survey/views.py
survey/migrations/0001_initial.py
survey/migrations/0002_alter_survey_description_alter_survey_end_date_and_more.py
survey/migrations/__init__.py
survey/templates/survey/survey_detail.html
survey/templates/survey/widgets/survey_chart.html
survey/templates/survey/widgets/survey_detail.html
survey/templates/survey/widgets/survey_header.html
survey/templates/survey/widgets/survey_option.html
survey/templatetags/__init__.py
survey/templatetags/survey.py
django_surveyplus-1.0.2.dist-info/METADATA
django_surveyplus-1.0.2.dist-info/WHEEL
django_surveyplus-1.0.2.dist-info/top_level.txt
django_surveyplus-1.0.2.dist-info/RECORD
